{"country":"United States","industry":"Staffing & Employment Services","sector":"Industrials","employees":1100,"phone":"714 921 8800","ceo":"Ms. Linda  Perneau","url":"http://www.volt.com","description":"Volt Information Sciences, Inc. provides traditional time, materials-based, and project-based staffing services in the United States, Europe, Canada, and the Asia Pacific. The company operates through North American Staffing, International Staffing, and North American MSP segments. It provides contingent staffing, direct placement, personnel recruitment, staffing management, and other employment services; and managed service programs consisting of managing the procurement, on-boarding of contingent workers, and specialized solutions, such as managing suppliers, sourcing and recruiting support, statement of work management, supplier performance measurement, optimization and analysis, benchmarking of spend demographics and market rate analysis, consolidated customer billing, and supplier payment management solutions. The company also offers call center and payroll services; recruitment process outsourcing; and customized talent and supplier management solutions, as well as act as a subcontractor or associate vendor to other national providers in their MSPs. It serves multinational, national, and local customers in various industries, including aerospace, automotive, banking and finance, consumer electronics, information technology, insurance, life science, manufacturing, media and entertainment, pharmaceutical, software, telecommunication, transportation, and utilities. The company was founded in 1950 and is headquartered in Orange, California.","exchange":"Nasdaq Global Select","symbol":"VOLT","exchangeSymbol":"NGS","hq_address":"2401 North","hq_state":"CA","hq_country":"United States","active":true}